{"title":{"0":"Piso en venta en Puerto Real","1":"Casa en venta en Puerto Real","2":"Casa en venta en Puerto Real","3":"Piso en venta en Puerto Real","4":"Piso en venta en Puerto Real","5":"Piso en venta en Puerto Real","6":"Casa en venta en Puerto Real","7":"Casa en venta en Puerto Real","8":"Piso en venta en Puerto Real","9":"Casa rural en venta en Puerto Real","10":"Piso en venta en Puerto Real","11":"Casa en venta en Puerto Real","12":"Casa rural en venta en Puerto Real","13":"Casa en venta en Puerto Real","14":"Piso en venta en Puerto Real","15":"Casa en venta en Puerto Real","16":"Casa rural en venta en Puerto Real","17":"Casa en venta en Puerto Real","18":"Edificio en venta en Puerto Real","19":"Casa en venta en Puerto Real","20":"Piso en venta en Puerto Real"},"price":{"0":184900,"1":194900,"2":149900,"3":135000,"4":119900,"5":204900,"6":205000,"7":179900,"8":121900,"9":149900,"10":98000,"11":195000,"12":169900,"13":276900,"14":105000,"15":244900,"16":179900,"17":219900,"18":600000,"19":249900,"20":119900},"location":{"0":"Puerto Real","1":"Puerto Real","2":"Puerto Real","3":"Puerto Real","4":"Puerto Real","5":"Puerto Real","6":"Puerto Real","7":"Puerto Real","8":"Puerto Real","9":"Puerto Real","10":"Puerto Real","11":"Puerto Real","12":"Puerto Real","13":"Puerto Real","14":"Puerto Real","15":"Puerto Real","16":"Puerto Real","17":"Puerto Real","18":"Puerto Real","19":"Puerto Real","20":"Puerto Real"},"rooms":{"0":3.0,"1":3.0,"2":2.0,"3":3.0,"4":3.0,"5":2.0,"6":3.0,"7":3.0,"8":3.0,"9":3.0,"10":3.0,"11":4.0,"12":3.0,"13":3.0,"14":3.0,"15":4.0,"16":6.0,"17":4.0,"18":null,"19":3.0,"20":4.0},"surface":{"0":113,"1":184,"2":127,"3":90,"4":84,"5":95,"6":178,"7":120,"8":83,"9":130,"10":88,"11":154,"12":110,"13":113,"14":94,"15":240,"16":137,"17":98,"18":411,"19":96,"20":88},"bathrooms":{"0":2.0,"1":2.0,"2":1.0,"3":2.0,"4":1.0,"5":2.0,"6":1.0,"7":1.0,"8":1.0,"9":1.0,"10":1.0,"11":2.0,"12":1.0,"13":2.0,"14":1.0,"15":2.0,"16":3.0,"17":2.0,"18":null,"19":1.0,"20":1.0},"Aire acondicionado:":{"0":"Centralizada","1":null,"2":null,"3":"Independiente","4":"Independiente","5":"Centralizada","6":"Independiente","7":null,"8":null,"9":null,"10":null,"11":null,"12":null,"13":"Independiente","14":null,"15":null,"16":"Independiente","17":"Independiente","18":"Independiente","19":"Centralizada","20":null},"Ascensor:":{"0":"S\u00ed","1":null,"2":null,"3":null,"4":null,"5":null,"6":null,"7":null,"8":null,"9":null,"10":null,"11":null,"12":null,"13":null,"14":"S\u00ed","15":null,"16":null,"17":null,"18":null,"19":null,"20":null},"Tipo de inmueble:":{"0":"Popular","1":"Media","2":"Popular","3":"Popular","4":"Popular","5":"Popular","6":"Media","7":"Media","8":"Popular","9":"Popular","10":"Popular","11":"Popular","12":"Media","13":"Popular","14":"Popular","15":"Media","16":"Popular","17":"Popular","18":"Popular","19":"Media","20":"Media"},"A\u00f1o de construcci\u00f3n:":{"0":"2008","1":"2005","2":"1889","3":"1994","4":"1997","5":"2012","6":"1970","7":"1995","8":"1973","9":"2005","10":"1982","11":"1890","12":"1995","13":"2007","14":"1974","15":"1890","16":"2001","17":"1994","18":"1890","19":"1984","20":"1974"},"Planta:":{"0":null,"1":null,"2":"Baja","3":"1 (planta media)","4":"1 (planta media)","5":null,"6":"1 (planta media)","7":"2 (planta baja)","8":null,"9":null,"10":"Media","11":"Baja","12":"Baja","13":null,"14":"2 (planta media)","15":"Baja","16":null,"17":null,"18":null,"19":"2 (planta media)","20":"3 (planta media)"},"A\u00f1o reforma edificio:":{"0":null,"1":null,"2":null,"3":null,"4":null,"5":null,"6":null,"7":null,"8":null,"9":null,"10":null,"11":null,"12":null,"13":null,"14":null,"15":null,"16":null,"17":null,"18":"2012","19":null,"20":null}}